{
  "OBJECT_API":"Meta_Studentdvdvdvd__c",
  "Fields":[
    {
      "API":"First_Name__c",
      "LABEL":"First Name",
      "LENGTH":20,
      "TYPE":"Text"
    },
    {
      "API":"Middle_Name__c",
      "LABEL":"Middle Name",
      "LENGTH":20,
      "TYPE":"Text"
    },
    {
      "API":"Last_Name__c",
      "LABEL":"Last Name",
      "LENGTH":20,
      "TYPE":"Text"
    },
    {
      "API":"Email__c",
      "LABEL":"Email",
      "TYPE":"Email",
      "EXTERNAL":true
    },
    {
      "API":"Number__c",
      "LABEL":"Number",
      "TYPE":"Number",
      "PRECISION":10,
      "SCALE":2,
      "UNIQUE":true
    },
    {
      "API":"Currency__c",
      "LABEL":"Currency",
      "TYPE":"Currency",
      "PRECISION":7,
      "SCALE":2,
      "REQUIRED":true
    },
    {
      "API":"Percent__c",
      "LABEL":"Percent",
      "TYPE":"Percent",
      "PRECISION":4,
      "SCALE":2
    },
    {
      "API":"Date__c",
      "LABEL":"Date",
      "TYPE":"Date"
    },
    {
      "API":"Phone__c",
      "LABEL":"Phone",
      "TYPE":"Phone"
    },
    {
      "API":"MetaLookup__c",
      "LABEL":"MetaLookup",
      "TYPE":"Lookup",
      "RELATION_LABEL":"MetaLookup",
      "RELATION_NAME":"MetaLookup",
      "REFERENCE_TO":"College__c"
    },
    {
      "API":"MetaMasterLookup__c",
      "LABEL":"MetaMasterLookup",
      "TYPE":"MasterDetail",
      "RELATION_LABEL":"MetaMasterLookup",
      "RELATION_NAME":"MetaMasterLookup",
      "REFERENCE_TO":"College__c",
      "WRITE_REQUIRES":false
    }
  ]
}